_swig_decoders.cpython-37m-darwin.so
ctc_decoders.py
swig_decoders.py
ctc_decoders-1.0.dist-info/METADATA
ctc_decoders-1.0.dist-info/WHEEL
ctc_decoders-1.0.dist-info/top_level.txt
ctc_decoders-1.0.dist-info/RECORD
