Metadata-Version: 2.1
Name: ctc-decoders
Version: 1.0
Summary: CTC decoders
Home-page: UNKNOWN
Author: UNKNOWN
Author-email: UNKNOWN
License: UNKNOWN
Platform: UNKNOWN
